code_mage/__init__.py
code_mage/api.py
code_mage/argsParser.py
code_mage/codeMage.py
code_mage/loadConfig.py
code_mage/translator.py
code_mage-1.1.2.dist-info/LICENSE
code_mage-1.1.2.dist-info/METADATA
code_mage-1.1.2.dist-info/WHEEL
code_mage-1.1.2.dist-info/entry_points.txt
code_mage-1.1.2.dist-info/RECORD
