Metadata-Version: 2.1
Name: code-mage
Version: 1.1.2
Summary: 
Author: gitdevjin
Author-email: dev.hjshin@gmail.com
Requires-Python: >=3.12,<4.0
Classifier: Programming Language :: Python :: 3
Classifier: Programming Language :: Python :: 3.12
Requires-Dist: openai (>=1.44.1,<2.0.0)
Requires-Dist: python-dotenv (>=1.0.1,<2.0.0)
Requires-Dist: toml (>=0.10.2,<0.11.0)
